{
    "datesOnCalendar": [
        "01/20/2023",
        "01/23/2023",
        "01/24/2023",
        "01/25/2023",
        "01/26/2023",
        "01/27/2023"
    ],
    "billsOnCalendar": [
        "HB 2",
        "HB 5",
        "HB 6",
        "HB 7",
        "HB 8",
        "HB 11",
        "HB 19",
        "HB 21",
        "HB 22",
        "HB 25",
        "HB 29",
        "HB 30",
        "HB 45",
        "HB 48",
        "HB 54",
        "HB 59",
        "HB 60",
        "HB 70",
        "HB 71",
        "HB 82",
        "HB 85",
        "HB 99",
        "HB 113",
        "HB 119",
        "HB 121",
        "HB 123",
        "HB 124",
        "HB 133",
        "HB 138",
        "HB 139",
        "HB 141",
        "HB 142",
        "HB 145",
        "HB 147",
        "HB 157",
        "HB 158",
        "HB 159",
        "HB 160",
        "HB 162",
        "HB 166",
        "HB 177",
        "HB 181",
        "HB 188",
        "HB 191",
        "HB 212",
        "HB 216",
        "HB 222",
        "HB 225",
        "HB 226",
        "HB 228",
        "HB 231",
        "HB 232",
        "HB 237",
        "HB 240",
        "HB 241",
        "HB 242",
        "HB 244",
        "HB 245",
        "HB 246",
        "HB 248",
        "HB 249",
        "HB 250",
        "HB 252",
        "HB 253",
        "HB 254",
        "HB 255",
        "HB 256",
        "HB 258",
        "HB 261",
        "HB 262",
        "HB 263",
        "HB 264",
        "HB 266",
        "HB 267",
        "HB 270",
        "HB 272",
        "HB 273",
        "HB 274",
        "HB 276",
        "HB 277",
        "HB 279",
        "HB 289",
        "HB 290",
        "HB 292",
        "HJ 1",
        "SB 3",
        "SB 6",
        "SB 18",
        "SB 20",
        "SB 21",
        "SB 34",
        "SB 35",
        "SB 40",
        "SB 45",
        "SB 51",
        "SB 55",
        "SB 58",
        "SB 62",
        "SB 70",
        "SB 80",
        "SB 83",
        "SB 90",
        "SB 95",
        "SB 102",
        "SB 129",
        "SB 140",
        "SB 153",
        "SB 156",
        "SB 161",
        "SB 162",
        "SB 163",
        "SB 165",
        "SB 167",
        "SB 174",
        "SB 177",
        "SB 178",
        "SB 179",
        "SB 180",
        "SB 181",
        "SB 182",
        "SB 183",
        "SB 184",
        "SB 186",
        "SB 187",
        "SB 188",
        "SB 191",
        "SB 195",
        "SB 196",
        "SJ 4",
        "SJ 6",
        "SJ 7",
        "SJ 8",
        "SR 6",
        "SR 8",
        "SR 9",
        "SR 10",
        "HB 74",
        "HB 75",
        "HB 151",
        "HB 169",
        "HB 170",
        "HB 178",
        "HB 183",
        "HB 205",
        "HB 209",
        "SB 17",
        "SB 33",
        "SB 50",
        "SB 64",
        "SB 81",
        "SB 132",
        "SB 149",
        "SB 155",
        "SJ 1",
        "HB 93",
        "HB 94",
        "HB 102",
        "HB 105",
        "HB 108",
        "HB 109",
        "HB 116",
        "HB 134",
        "HB 143",
        "SB 27",
        "SB 78",
        "SB 111",
        "SB 116",
        "SB 130",
        "SB 131",
        "SB 152",
        "SJ 3"
    ],
    "scheduledHearings": [
        {
            "id": "HB2-0057",
            "bill": "HB 2",
            "date": "01/20/2023",
            "description": "Hearing",
            "posession": "house",
            "committee": "Joint Appropriations Section E — Education",
            "actionUrl": null,
            "recordings": [],
            "key": "Hearing",
            "isMajor": true,
            "hearing": true
        },
        {
            "id": "HB2-0058",
            "bill": "HB 2",
            "date": "01/20/2023",
            "description": "Hearing",
            "posession": "house",
            "committee": "Joint Appropriations Section D — Judicial Branch, Law Enforcement, and Justice",
            "actionUrl": null,
            "recordings": [],
            "key": "Hearing",
            "isMajor": true,
            "hearing": true
        },
        {
            "id": "HB2-0059",
            "bill": "HB 2",
            "date": "01/20/2023",
            "description": "Hearing",
            "posession": "house",
            "committee": "Joint Appropriations Section B — Health and Human Services",
            "actionUrl": null,
            "recordings": [],
            "key": "Hearing",
            "isMajor": true,
            "hearing": true
        },
        {
            "id": "HB2-0060",
            "bill": "HB 2",
            "date": "01/20/2023",
            "description": "Hearing",
            "posession": "house",
            "committee": "Joint Appropriations Section A — General Government",
            "actionUrl": null,
            "recordings": [],
            "key": "Hearing",
            "isMajor": true,
            "hearing": true
        },
        {
            "id": "HB2-0061",
            "bill": "HB 2",
            "date": "01/20/2023",
            "description": "Hearing",
            "posession": "house",
            "committee": "Joint Appropriations Section E — Education",
            "actionUrl": null,
            "recordings": [],
            "key": "Hearing",
            "isMajor": true,
            "hearing": true
        },
        {
            "id": "HB2-0062",
            "bill": "HB 2",
            "date": "01/23/2023",
            "description": "Hearing",
            "posession": "house",
            "committee": "Joint Appropriations Section E — Education",
            "actionUrl": null,
            "recordings": [],
            "key": "Hearing",
            "isMajor": true,
            "hearing": true
        },
        {
            "id": "HB2-0063",
            "bill": "HB 2",
            "date": "01/23/2023",
            "description": "Hearing",
            "posession": "house",
            "committee": "Joint Appropriations Section D — Judicial Branch, Law Enforcement, and Justice",
            "actionUrl": null,
            "recordings": [],
            "key": "Hearing",
            "isMajor": true,
            "hearing": true
        },
        {
            "id": "HB2-0064",
            "bill": "HB 2",
            "date": "01/23/2023",
            "description": "Hearing",
            "posession": "house",
            "committee": "Joint Appropriations Section C — Natural Resources and Transportation",
            "actionUrl": null,
            "recordings": [],
            "key": "Hearing",
            "isMajor": true,
            "hearing": true
        },
        {
            "id": "HB2-0065",
            "bill": "HB 2",
            "date": "01/23/2023",
            "description": "Hearing",
            "posession": "house",
            "committee": "Joint Appropriations Section B — Health and Human Services",
            "actionUrl": null,
            "recordings": [],
            "key": "Hearing",
            "isMajor": true,
            "hearing": true
        },
        {
            "id": "HB2-0066",
            "bill": "HB 2",
            "date": "01/23/2023",
            "description": "Hearing",
            "posession": "house",
            "committee": "Joint Appropriations Section A — General Government",
            "actionUrl": null,
            "recordings": [],
            "key": "Hearing",
            "isMajor": true,
            "hearing": true
        },
        {
            "id": "HB2-0067",
            "bill": "HB 2",
            "date": "01/24/2023",
            "description": "Hearing",
            "posession": "house",
            "committee": "Joint Appropriations Section D — Judicial Branch, Law Enforcement, and Justice",
            "actionUrl": null,
            "recordings": [],
            "key": "Hearing",
            "isMajor": true,
            "hearing": true
        },
        {
            "id": "HB2-0068",
            "bill": "HB 2",
            "date": "01/24/2023",
            "description": "Hearing",
            "posession": "house",
            "committee": "Joint Appropriations Section A — General Government",
            "actionUrl": null,
            "recordings": [],
            "key": "Hearing",
            "isMajor": true,
            "hearing": true
        },
        {
            "id": "HB2-0069",
            "bill": "HB 2",
            "date": "01/24/2023",
            "description": "Hearing",
            "posession": "house",
            "committee": "Joint Appropriations Section E — Education",
            "actionUrl": null,
            "recordings": [],
            "key": "Hearing",
            "isMajor": true,
            "hearing": true
        },
        {
            "id": "HB2-0070",
            "bill": "HB 2",
            "date": "01/24/2023",
            "description": "Hearing",
            "posession": "house",
            "committee": "Joint Appropriations Section C — Natural Resources and Transportation",
            "actionUrl": null,
            "recordings": [],
            "key": "Hearing",
            "isMajor": true,
            "hearing": true
        },
        {
            "id": "HB2-0071",
            "bill": "HB 2",
            "date": "01/24/2023",
            "description": "Hearing",
            "posession": "house",
            "committee": "Joint Appropriations Section B — Health and Human Services",
            "actionUrl": null,
            "recordings": [],
            "key": "Hearing",
            "isMajor": true,
            "hearing": true
        },
        {
            "id": "HB2-0072",
            "bill": "HB 2",
            "date": "01/25/2023",
            "description": "Hearing",
            "posession": "house",
            "committee": "Joint Appropriations Section C — Natural Resources and Transportation",
            "actionUrl": null,
            "recordings": [],
            "key": "Hearing",
            "isMajor": true,
            "hearing": true
        },
        {
            "id": "HB2-0073",
            "bill": "HB 2",
            "date": "01/25/2023",
            "description": "Hearing",
            "posession": "house",
            "committee": "Joint Appropriations Section B — Health and Human Services",
            "actionUrl": null,
            "recordings": [],
            "key": "Hearing",
            "isMajor": true,
            "hearing": true
        },
        {
            "id": "HB2-0074",
            "bill": "HB 2",
            "date": "01/25/2023",
            "description": "Hearing",
            "posession": "house",
            "committee": "Joint Appropriations Section A — General Government",
            "actionUrl": null,
            "recordings": [],
            "key": "Hearing",
            "isMajor": true,
            "hearing": true
        },
        {
            "id": "HB2-0075",
            "bill": "HB 2",
            "date": "01/25/2023",
            "description": "Hearing",
            "posession": "house",
            "committee": "Joint Appropriations Section C — Natural Resources and Transportation",
            "actionUrl": null,
            "recordings": [],
            "key": "Hearing",
            "isMajor": true,
            "hearing": true
        },
        {
            "id": "HB2-0076",
            "bill": "HB 2",
            "date": "01/26/2023",
            "description": "Hearing",
            "posession": "house",
            "committee": "Joint Appropriations Section D — Judicial Branch, Law Enforcement, and Justice",
            "actionUrl": null,
            "recordings": [],
            "key": "Hearing",
            "isMajor": true,
            "hearing": true
        },
        {
            "id": "HB2-0077",
            "bill": "HB 2",
            "date": "01/26/2023",
            "description": "Hearing",
            "posession": "house",
            "committee": "Joint Appropriations Section B — Health and Human Services",
            "actionUrl": null,
            "recordings": [],
            "key": "Hearing",
            "isMajor": true,
            "hearing": true
        },
        {
            "id": "HB2-0078",
            "bill": "HB 2",
            "date": "01/26/2023",
            "description": "Hearing",
            "posession": "house",
            "committee": "Joint Appropriations Section A — General Government",
            "actionUrl": null,
            "recordings": [],
            "key": "Hearing",
            "isMajor": true,
            "hearing": true
        },
        {
            "id": "HB2-0079",
            "bill": "HB 2",
            "date": "01/26/2023",
            "description": "Hearing",
            "posession": "house",
            "committee": "Joint Appropriations Section E — Education",
            "actionUrl": null,
            "recordings": [],
            "key": "Hearing",
            "isMajor": true,
            "hearing": true
        },
        {
            "id": "HB2-0080",
            "bill": "HB 2",
            "date": "01/26/2023",
            "description": "Hearing",
            "posession": "house",
            "committee": "Joint Appropriations Section C — Natural Resources and Transportation",
            "actionUrl": null,
            "recordings": [],
            "key": "Hearing",
            "isMajor": true,
            "hearing": true
        },
        {
            "id": "HB2-0081",
            "bill": "HB 2",
            "date": "01/27/2023",
            "description": "Hearing",
            "posession": "house",
            "committee": "Joint Appropriations Section B — Health and Human Services",
            "actionUrl": null,
            "recordings": [],
            "key": "Hearing",
            "isMajor": true,
            "hearing": true
        },
        {
            "id": "HB5-0021",
            "bill": "HB 5",
            "date": "01/25/2023",
            "description": "Hearing",
            "posession": "house",
            "committee": "Joint Appropriations Section F — Long-Range Planning",
            "actionUrl": null,
            "recordings": [],
            "key": "Hearing",
            "isMajor": true,
            "hearing": true
        },
        {
            "id": "HB5-0022",
            "bill": "HB 5",
            "date": "01/26/2023",
            "description": "Hearing",
            "posession": "house",
            "committee": "Joint Appropriations Section F — Long-Range Planning",
            "actionUrl": null,
            "recordings": [],
            "key": "Hearing",
            "isMajor": true,
            "hearing": true
        },
        {
            "id": "HB5-0023",
            "bill": "HB 5",
            "date": "01/27/2023",
            "description": "Hearing",
            "posession": "house",
            "committee": "Joint Appropriations Section F — Long-Range Planning",
            "actionUrl": null,
            "recordings": [],
            "key": "Hearing",
            "isMajor": true,
            "hearing": true
        },
        {
            "id": "HB6-0016",
            "bill": "HB 6",
            "date": "01/20/2023",
            "description": "Hearing",
            "posession": "house",
            "committee": "Joint Appropriations Section F — Long-Range Planning",
            "actionUrl": null,
            "recordings": [],
            "key": "Hearing",
            "isMajor": true,
            "hearing": true
        },
        {
            "id": "HB7-0013",
            "bill": "HB 7",
            "date": "01/24/2023",
            "description": "Hearing",
            "posession": "house",
            "committee": "Joint Appropriations Section F — Long-Range Planning",
            "actionUrl": null,
            "recordings": [],
            "key": "Hearing",
            "isMajor": true,
            "hearing": true
        },
        {
            "id": "HB8-0018",
            "bill": "HB 8",
            "date": "01/23/2023",
            "description": "Hearing",
            "posession": "house",
            "committee": "Joint Appropriations Section F — Long-Range Planning",
            "actionUrl": null,
            "recordings": [],
            "key": "Hearing",
            "isMajor": true,
            "hearing": true
        },
        {
            "id": "HB11-0016",
            "bill": "HB 11",
            "date": "01/20/2023",
            "description": "Hearing",
            "posession": "house",
            "committee": "Joint Appropriations Section F — Long-Range Planning",
            "actionUrl": null,
            "recordings": [],
            "key": "Hearing",
            "isMajor": true,
            "hearing": true
        },
        {
            "id": "HB11-0017",
            "bill": "HB 11",
            "date": "01/23/2023",
            "description": "Hearing",
            "posession": "house",
            "committee": "Joint Appropriations Section F — Long-Range Planning",
            "actionUrl": null,
            "recordings": [],
            "key": "Hearing",
            "isMajor": true,
            "hearing": true
        },
        {
            "id": "HB19-0025",
            "bill": "HB 19",
            "date": "01/24/2023",
            "description": "Hearing",
            "posession": "house",
            "committee": "House Appropriations",
            "actionUrl": null,
            "recordings": [],
            "key": "Hearing",
            "isMajor": true,
            "hearing": true
        },
        {
            "id": "HB21-0023",
            "bill": "HB 21",
            "date": "01/23/2023",
            "description": "Hearing",
            "posession": "senate",
            "committee": "Senate Education and Cultural Resources",
            "actionUrl": null,
            "recordings": [],
            "key": "Hearing",
            "isMajor": true,
            "hearing": true
        },
        {
            "id": "HB22-0028",
            "bill": "HB 22",
            "date": "01/23/2023",
            "description": "Hearing",
            "posession": "senate",
            "committee": "Senate Education and Cultural Resources",
            "actionUrl": null,
            "recordings": [],
            "key": "Hearing",
            "isMajor": true,
            "hearing": true
        },
        {
            "id": "HB25-0031",
            "bill": "HB 25",
            "date": "01/24/2023",
            "description": "Hearing",
            "posession": "senate",
            "committee": "Senate Taxation",
            "actionUrl": null,
            "recordings": [],
            "key": "Hearing",
            "isMajor": true,
            "hearing": true
        },
        {
            "id": "HB29-0028",
            "bill": "HB 29",
            "date": "01/24/2023",
            "description": "Hearing",
            "posession": "house",
            "committee": "House Appropriations",
            "actionUrl": null,
            "recordings": [],
            "key": "Hearing",
            "isMajor": true,
            "hearing": true
        },
        {
            "id": "HB30-0038",
            "bill": "HB 30",
            "date": "01/23/2023",
            "description": "Hearing",
            "posession": "senate",
            "committee": "Senate Business, Labor, and Economic Affairs",
            "actionUrl": null,
            "recordings": [],
            "key": "Hearing",
            "isMajor": true,
            "hearing": true
        },
        {
            "id": "HB45-0020",
            "bill": "HB 45",
            "date": "01/25/2023",
            "description": "Hearing",
            "posession": "house",
            "committee": "House Human Services",
            "actionUrl": null,
            "recordings": [],
            "key": "Hearing",
            "isMajor": true,
            "hearing": true
        },
        {
            "id": "HB48-0030",
            "bill": "HB 48",
            "date": "01/24/2023",
            "description": "Hearing",
            "posession": "senate",
            "committee": "Senate Business, Labor, and Economic Affairs",
            "actionUrl": null,
            "recordings": [],
            "key": "Hearing",
            "isMajor": true,
            "hearing": true
        },
        {
            "id": "HB54-0023",
            "bill": "HB 54",
            "date": "01/25/2023",
            "description": "Hearing",
            "posession": "senate",
            "committee": "Senate Natural Resources",
            "actionUrl": null,
            "recordings": [],
            "key": "Hearing",
            "isMajor": true,
            "hearing": true
        },
        {
            "id": "HB59-0032",
            "bill": "HB 59",
            "date": "01/24/2023",
            "description": "Hearing",
            "posession": "senate",
            "committee": "Senate Agriculture, Livestock and Irrigation",
            "actionUrl": null,
            "recordings": [],
            "key": "Hearing",
            "isMajor": true,
            "hearing": true
        },
        {
            "id": "HB60-0028",
            "bill": "HB 60",
            "date": "01/23/2023",
            "description": "Hearing",
            "posession": "house",
            "committee": "House Appropriations",
            "actionUrl": null,
            "recordings": [],
            "key": "Hearing",
            "isMajor": true,
            "hearing": true
        },
        {
            "id": "HB70-0025",
            "bill": "HB 70",
            "date": "01/24/2023",
            "description": "Hearing",
            "posession": "senate",
            "committee": "Senate Business, Labor, and Economic Affairs",
            "actionUrl": null,
            "recordings": [],
            "key": "Hearing",
            "isMajor": true,
            "hearing": true
        },
        {
            "id": "HB71-0030",
            "bill": "HB 71",
            "date": "01/20/2023",
            "description": "Hearing",
            "posession": "senate",
            "committee": "Senate Business, Labor, and Economic Affairs",
            "actionUrl": null,
            "recordings": [],
            "key": "Hearing",
            "isMajor": true,
            "hearing": true
        },
        {
            "id": "HB82-0026",
            "bill": "HB 82",
            "date": "01/25/2023",
            "description": "Hearing",
            "posession": "house",
            "committee": "House Appropriations",
            "actionUrl": null,
            "recordings": [],
            "key": "Hearing",
            "isMajor": true,
            "hearing": true
        },
        {
            "id": "HB85-0025",
            "bill": "HB 85",
            "date": "01/24/2023",
            "description": "Hearing",
            "posession": "senate",
            "committee": "Senate Agriculture, Livestock and Irrigation",
            "actionUrl": null,
            "recordings": [],
            "key": "Hearing",
            "isMajor": true,
            "hearing": true
        },
        {
            "id": "HB99-0023",
            "bill": "HB 99",
            "date": "01/24/2023",
            "description": "Hearing",
            "posession": "senate",
            "committee": "Senate Fish and Game",
            "actionUrl": null,
            "recordings": [],
            "key": "Hearing",
            "isMajor": true,
            "hearing": true
        },
        {
            "id": "HB113-0024",
            "bill": "HB 113",
            "date": "01/23/2023",
            "description": "Hearing",
            "posession": "senate",
            "committee": "Senate Local Government",
            "actionUrl": null,
            "recordings": [],
            "key": "Hearing",
            "isMajor": true,
            "hearing": true
        },
        {
            "id": "HB119-0023",
            "bill": "HB 119",
            "date": "01/26/2023",
            "description": "Hearing",
            "posession": "house",
            "committee": "House Appropriations",
            "actionUrl": null,
            "recordings": [],
            "key": "Hearing",
            "isMajor": true,
            "hearing": true
        },
        {
            "id": "HB121-0029",
            "bill": "HB 121",
            "date": "01/24/2023",
            "description": "Hearing",
            "posession": "senate",
            "committee": "Senate Taxation",
            "actionUrl": null,
            "recordings": [],
            "key": "Hearing",
            "isMajor": true,
            "hearing": true
        },
        {
            "id": "HB123-0026",
            "bill": "HB 123",
            "date": "01/24/2023",
            "description": "Hearing",
            "posession": "senate",
            "committee": "Senate Business, Labor, and Economic Affairs",
            "actionUrl": null,
            "recordings": [],
            "key": "Hearing",
            "isMajor": true,
            "hearing": true
        },
        {
            "id": "HB124-0025",
            "bill": "HB 124",
            "date": "01/24/2023",
            "description": "Hearing",
            "posession": "senate",
            "committee": "Senate Taxation",
            "actionUrl": null,
            "recordings": [],
            "key": "Hearing",
            "isMajor": true,
            "hearing": true
        },
        {
            "id": "HB133-0023",
            "bill": "HB 133",
            "date": "01/24/2023",
            "description": "Hearing",
            "posession": "senate",
            "committee": "Senate Fish and Game",
            "actionUrl": null,
            "recordings": [],
            "key": "Hearing",
            "isMajor": true,
            "hearing": true
        },
        {
            "id": "HB138-0036",
            "bill": "HB 138",
            "date": "01/23/2023",
            "description": "Hearing",
            "posession": "senate",
            "committee": "Senate Business, Labor, and Economic Affairs",
            "actionUrl": null,
            "recordings": [],
            "key": "Hearing",
            "isMajor": true,
            "hearing": true
        },
        {
            "id": "HB139-0027",
            "bill": "HB 139",
            "date": "01/23/2023",
            "description": "Hearing",
            "posession": "senate",
            "committee": "Senate Business, Labor, and Economic Affairs",
            "actionUrl": null,
            "recordings": [],
            "key": "Hearing",
            "isMajor": true,
            "hearing": true
        },
        {
            "id": "HB141-0024",
            "bill": "HB 141",
            "date": "01/23/2023",
            "description": "Hearing",
            "posession": "house",
            "committee": "House Appropriations",
            "actionUrl": null,
            "recordings": [],
            "key": "Hearing",
            "isMajor": true,
            "hearing": true
        },
        {
            "id": "HB142-0025",
            "bill": "HB 142",
            "date": "01/25/2023",
            "description": "Hearing",
            "posession": "senate",
            "committee": "Senate Business, Labor, and Economic Affairs",
            "actionUrl": null,
            "recordings": [],
            "key": "Hearing",
            "isMajor": true,
            "hearing": true
        },
        {
            "id": "HB145-0024",
            "bill": "HB 145",
            "date": "01/24/2023",
            "description": "Hearing",
            "posession": "senate",
            "committee": "Senate Business, Labor, and Economic Affairs",
            "actionUrl": null,
            "recordings": [],
            "key": "Hearing",
            "isMajor": true,
            "hearing": true
        },
        {
            "id": "HB147-0025",
            "bill": "HB 147",
            "date": "01/24/2023",
            "description": "Hearing",
            "posession": "house",
            "committee": "House Appropriations",
            "actionUrl": null,
            "recordings": [],
            "key": "Hearing",
            "isMajor": true,
            "hearing": true
        },
        {
            "id": "HB157-0024",
            "bill": "HB 157",
            "date": "01/24/2023",
            "description": "Hearing",
            "posession": "senate",
            "committee": "Senate Business, Labor, and Economic Affairs",
            "actionUrl": null,
            "recordings": [],
            "key": "Hearing",
            "isMajor": true,
            "hearing": true
        },
        {
            "id": "HB158-0014",
            "bill": "HB 158",
            "date": "01/24/2023",
            "description": "Hearing",
            "posession": "house",
            "committee": "House Agriculture",
            "actionUrl": null,
            "recordings": [],
            "key": "Hearing",
            "isMajor": true,
            "hearing": true
        },
        {
            "id": "HB159-0019",
            "bill": "HB 159",
            "date": "01/24/2023",
            "description": "Hearing",
            "posession": "house",
            "committee": "House Agriculture",
            "actionUrl": null,
            "recordings": [],
            "key": "Hearing",
            "isMajor": true,
            "hearing": true
        },
        {
            "id": "HB160-0025",
            "bill": "HB 160",
            "date": "01/20/2023",
            "description": "Hearing",
            "posession": "senate",
            "committee": "Senate Business, Labor, and Economic Affairs",
            "actionUrl": null,
            "recordings": [],
            "key": "Hearing",
            "isMajor": true,
            "hearing": true
        },
        {
            "id": "HB162-0025",
            "bill": "HB 162",
            "date": "01/24/2023",
            "description": "Hearing",
            "posession": "senate",
            "committee": "Senate Fish and Game",
            "actionUrl": null,
            "recordings": [],
            "key": "Hearing",
            "isMajor": true,
            "hearing": true
        },
        {
            "id": "HB166-0027",
            "bill": "HB 166",
            "date": "01/24/2023",
            "description": "Hearing",
            "posession": "senate",
            "committee": "Senate Business, Labor, and Economic Affairs",
            "actionUrl": null,
            "recordings": [],
            "key": "Hearing",
            "isMajor": true,
            "hearing": true
        },
        {
            "id": "HB177-0024",
            "bill": "HB 177",
            "date": "01/20/2023",
            "description": "Hearing",
            "posession": "house",
            "committee": "House Business and Labor",
            "actionUrl": null,
            "recordings": [],
            "key": "Hearing",
            "isMajor": true,
            "hearing": true
        },
        {
            "id": "HB181-0018",
            "bill": "HB 181",
            "date": "01/20/2023",
            "description": "Hearing",
            "posession": "house",
            "committee": "House Education",
            "actionUrl": null,
            "recordings": [],
            "key": "Hearing",
            "isMajor": true,
            "hearing": true
        },
        {
            "id": "HB188-0032",
            "bill": "HB 188",
            "date": "01/25/2023",
            "description": "Hearing",
            "posession": "house",
            "committee": "House Appropriations",
            "actionUrl": null,
            "recordings": [],
            "key": "Hearing",
            "isMajor": true,
            "hearing": true
        },
        {
            "id": "HB191-0019",
            "bill": "HB 191",
            "date": "01/23/2023",
            "description": "Hearing",
            "posession": "house",
            "committee": "House Energy, Technology and Federal Relations",
            "actionUrl": null,
            "recordings": [],
            "key": "Hearing",
            "isMajor": true,
            "hearing": true
        },
        {
            "id": "HB212-0034",
            "bill": "HB 212",
            "date": "01/23/2023",
            "description": "Hearing",
            "posession": "house",
            "committee": "House Appropriations",
            "actionUrl": null,
            "recordings": [],
            "key": "Hearing",
            "isMajor": true,
            "hearing": true
        },
        {
            "id": "HB216-0019",
            "bill": "HB 216",
            "date": "01/24/2023",
            "description": "Hearing",
            "posession": "house",
            "committee": "House State Administration",
            "actionUrl": null,
            "recordings": [],
            "key": "Hearing",
            "isMajor": true,
            "hearing": true
        },
        {
            "id": "HB222-0030",
            "bill": "HB 222",
            "date": "01/23/2023",
            "description": "Hearing",
            "posession": "house",
            "committee": "House Appropriations",
            "actionUrl": null,
            "recordings": [],
            "key": "Hearing",
            "isMajor": true,
            "hearing": true
        },
        {
            "id": "HB225-0023",
            "bill": "HB 225",
            "date": "01/24/2023",
            "description": "Hearing",
            "posession": "house",
            "committee": "House Taxation",
            "actionUrl": null,
            "recordings": [],
            "key": "Hearing",
            "isMajor": true,
            "hearing": true
        },
        {
            "id": "HB226-0022",
            "bill": "HB 226",
            "date": "01/23/2023",
            "description": "Hearing",
            "posession": "house",
            "committee": "House State Administration",
            "actionUrl": null,
            "recordings": [],
            "key": "Hearing",
            "isMajor": true,
            "hearing": true
        },
        {
            "id": "HB228-0022",
            "bill": "HB 228",
            "date": "01/20/2023",
            "description": "Hearing",
            "posession": "house",
            "committee": "House Judiciary",
            "actionUrl": null,
            "recordings": [],
            "key": "Hearing",
            "isMajor": true,
            "hearing": true
        },
        {
            "id": "HB231-0021",
            "bill": "HB 231",
            "date": "01/20/2023",
            "description": "Hearing",
            "posession": "house",
            "committee": "House Education",
            "actionUrl": null,
            "recordings": [],
            "key": "Hearing",
            "isMajor": true,
            "hearing": true
        },
        {
            "id": "HB232-0022",
            "bill": "HB 232",
            "date": "01/23/2023",
            "description": "Hearing",
            "posession": "house",
            "committee": "House State Administration",
            "actionUrl": null,
            "recordings": [],
            "key": "Hearing",
            "isMajor": true,
            "hearing": true
        },
        {
            "id": "HB237-0017",
            "bill": "HB 237",
            "date": "01/20/2023",
            "description": "Hearing",
            "posession": "house",
            "committee": "House Judiciary",
            "actionUrl": null,
            "recordings": [],
            "key": "Hearing",
            "isMajor": true,
            "hearing": true
        },
        {
            "id": "HB240-0018",
            "bill": "HB 240",
            "date": "01/20/2023",
            "description": "Hearing",
            "posession": "house",
            "committee": "House Education",
            "actionUrl": null,
            "recordings": [],
            "key": "Hearing",
            "isMajor": true,
            "hearing": true
        },
        {
            "id": "HB241-0022",
            "bill": "HB 241",
            "date": "01/24/2023",
            "description": "Hearing",
            "posession": "house",
            "committee": "House Local Government",
            "actionUrl": null,
            "recordings": [],
            "key": "Hearing",
            "isMajor": true,
            "hearing": true
        },
        {
            "id": "HB242-0022",
            "bill": "HB 242",
            "date": "01/20/2023",
            "description": "Hearing",
            "posession": "house",
            "committee": "House Business and Labor",
            "actionUrl": null,
            "recordings": [],
            "key": "Hearing",
            "isMajor": true,
            "hearing": true
        },
        {
            "id": "HB244-0022",
            "bill": "HB 244",
            "date": "01/23/2023",
            "description": "Hearing",
            "posession": "house",
            "committee": "House Appropriations",
            "actionUrl": null,
            "recordings": [],
            "key": "Hearing",
            "isMajor": true,
            "hearing": true
        },
        {
            "id": "HB245-0026",
            "bill": "HB 245",
            "date": "01/23/2023",
            "description": "Hearing",
            "posession": "house",
            "committee": "House Appropriations",
            "actionUrl": null,
            "recordings": [],
            "key": "Hearing",
            "isMajor": true,
            "hearing": true
        },
        {
            "id": "HB246-0016",
            "bill": "HB 246",
            "date": "01/26/2023",
            "description": "Hearing",
            "posession": "house",
            "committee": "House Local Government",
            "actionUrl": null,
            "recordings": [],
            "key": "Hearing",
            "isMajor": true,
            "hearing": true
        },
        {
            "id": "HB248-0018",
            "bill": "HB 248",
            "date": "01/23/2023",
            "description": "Hearing",
            "posession": "house",
            "committee": "House Human Services",
            "actionUrl": null,
            "recordings": [],
            "key": "Hearing",
            "isMajor": true,
            "hearing": true
        },
        {
            "id": "HB249-0027",
            "bill": "HB 249",
            "date": "01/20/2023",
            "description": "Hearing",
            "posession": "house",
            "committee": "House Taxation",
            "actionUrl": null,
            "recordings": [],
            "key": "Hearing",
            "isMajor": true,
            "hearing": true
        },
        {
            "id": "HB250-0017",
            "bill": "HB 250",
            "date": "01/24/2023",
            "description": "Hearing",
            "posession": "house",
            "committee": "House Business and Labor",
            "actionUrl": null,
            "recordings": [],
            "key": "Hearing",
            "isMajor": true,
            "hearing": true
        },
        {
            "id": "HB252-0022",
            "bill": "HB 252",
            "date": "01/25/2023",
            "description": "Hearing",
            "posession": "house",
            "committee": "House Human Services",
            "actionUrl": null,
            "recordings": [],
            "key": "Hearing",
            "isMajor": true,
            "hearing": true
        },
        {
            "id": "HB253-0023",
            "bill": "HB 253",
            "date": "01/20/2023",
            "description": "Hearing",
            "posession": "house",
            "committee": "House Taxation",
            "actionUrl": null,
            "recordings": [],
            "key": "Hearing",
            "isMajor": true,
            "hearing": true
        },
        {
            "id": "HB254-0018",
            "bill": "HB 254",
            "date": "01/24/2023",
            "description": "Hearing",
            "posession": "house",
            "committee": "House Business and Labor",
            "actionUrl": null,
            "recordings": [],
            "key": "Hearing",
            "isMajor": true,
            "hearing": true
        },
        {
            "id": "HB255-0021",
            "bill": "HB 255",
            "date": "01/23/2023",
            "description": "Hearing",
            "posession": "house",
            "committee": "House Judiciary",
            "actionUrl": null,
            "recordings": [],
            "key": "Hearing",
            "isMajor": true,
            "hearing": true
        },
        {
            "id": "HB256-0020",
            "bill": "HB 256",
            "date": "01/20/2023",
            "description": "Hearing",
            "posession": "house",
            "committee": "House Judiciary",
            "actionUrl": null,
            "recordings": [],
            "key": "Hearing",
            "isMajor": true,
            "hearing": true
        },
        {
            "id": "HB258-0026",
            "bill": "HB 258",
            "date": "01/24/2023",
            "description": "Hearing",
            "posession": "house",
            "committee": "House Appropriations",
            "actionUrl": null,
            "recordings": [],
            "key": "Hearing",
            "isMajor": true,
            "hearing": true
        },
        {
            "id": "HB261-0031",
            "bill": "HB 261",
            "date": "01/23/2023",
            "description": "Hearing",
            "posession": "house",
            "committee": "House Transportation",
            "actionUrl": null,
            "recordings": [],
            "key": "Hearing",
            "isMajor": true,
            "hearing": true
        },
        {
            "id": "HB262-0031",
            "bill": "HB 262",
            "date": "01/24/2023",
            "description": "Hearing",
            "posession": "house",
            "committee": "House Local Government",
            "actionUrl": null,
            "recordings": [],
            "key": "Hearing",
            "isMajor": true,
            "hearing": true
        },
        {
            "id": "HB263-0018",
            "bill": "HB 263",
            "date": "01/26/2023",
            "description": "Hearing",
            "posession": "house",
            "committee": "House Business and Labor",
            "actionUrl": null,
            "recordings": [],
            "key": "Hearing",
            "isMajor": true,
            "hearing": true
        },
        {
            "id": "HB264-0026",
            "bill": "HB 264",
            "date": "01/23/2023",
            "description": "Hearing",
            "posession": "house",
            "committee": "House Human Services",
            "actionUrl": null,
            "recordings": [],
            "key": "Hearing",
            "isMajor": true,
            "hearing": true
        },
        {
            "id": "HB266-0019",
            "bill": "HB 266",
            "date": "01/23/2023",
            "description": "Hearing",
            "posession": "house",
            "committee": "House Judiciary",
            "actionUrl": null,
            "recordings": [],
            "key": "Hearing",
            "isMajor": true,
            "hearing": true
        },
        {
            "id": "HB267-0024",
            "bill": "HB 267",
            "date": "01/24/2023",
            "description": "Hearing",
            "posession": "house",
            "committee": "House Appropriations",
            "actionUrl": null,
            "recordings": [],
            "key": "Hearing",
            "isMajor": true,
            "hearing": true
        },
        {
            "id": "HB270-0023",
            "bill": "HB 270",
            "date": "01/25/2023",
            "description": "Hearing",
            "posession": "house",
            "committee": "House Appropriations",
            "actionUrl": null,
            "recordings": [],
            "key": "Hearing",
            "isMajor": true,
            "hearing": true
        },
        {
            "id": "HB272-0017",
            "bill": "HB 272",
            "date": "01/23/2023",
            "description": "Hearing",
            "posession": "house",
            "committee": "House Judiciary",
            "actionUrl": null,
            "recordings": [],
            "key": "Hearing",
            "isMajor": true,
            "hearing": true
        },
        {
            "id": "HB273-0022",
            "bill": "HB 273",
            "date": "01/26/2023",
            "description": "Hearing",
            "posession": "house",
            "committee": "House Business and Labor",
            "actionUrl": null,
            "recordings": [],
            "key": "Hearing",
            "isMajor": true,
            "hearing": true
        },
        {
            "id": "HB274-0020",
            "bill": "HB 274",
            "date": "01/24/2023",
            "description": "Hearing",
            "posession": "house",
            "committee": "House Appropriations",
            "actionUrl": null,
            "recordings": [],
            "key": "Hearing",
            "isMajor": true,
            "hearing": true
        },
        {
            "id": "HB276-0020",
            "bill": "HB 276",
            "date": "01/24/2023",
            "description": "Hearing",
            "posession": "house",
            "committee": "House Agriculture",
            "actionUrl": null,
            "recordings": [],
            "key": "Hearing",
            "isMajor": true,
            "hearing": true
        },
        {
            "id": "HB277-0017",
            "bill": "HB 277",
            "date": "01/27/2023",
            "description": "Hearing",
            "posession": "house",
            "committee": "House Business and Labor",
            "actionUrl": null,
            "recordings": [],
            "key": "Hearing",
            "isMajor": true,
            "hearing": true
        },
        {
            "id": "HB279-0017",
            "bill": "HB 279",
            "date": "01/24/2023",
            "description": "Hearing",
            "posession": "house",
            "committee": "House Business and Labor",
            "actionUrl": null,
            "recordings": [],
            "key": "Hearing",
            "isMajor": true,
            "hearing": true
        },
        {
            "id": "HB289-0018",
            "bill": "HB 289",
            "date": "01/23/2023",
            "description": "Hearing",
            "posession": "house",
            "committee": "House Natural Resources",
            "actionUrl": null,
            "recordings": [],
            "key": "Hearing",
            "isMajor": true,
            "hearing": true
        },
        {
            "id": "HB290-0018",
            "bill": "HB 290",
            "date": "01/24/2023",
            "description": "Hearing",
            "posession": "house",
            "committee": "House Fish, Wildlife and Parks",
            "actionUrl": null,
            "recordings": [],
            "key": "Hearing",
            "isMajor": true,
            "hearing": true
        },
        {
            "id": "HB292-0019",
            "bill": "HB 292",
            "date": "01/26/2023",
            "description": "Hearing",
            "posession": "house",
            "committee": "House Appropriations",
            "actionUrl": null,
            "recordings": [],
            "key": "Hearing",
            "isMajor": true,
            "hearing": true
        },
        {
            "id": "HJ1-0028",
            "bill": "HJ 1",
            "date": "01/20/2023",
            "description": "Hearing",
            "posession": "senate",
            "committee": "Senate Judiciary",
            "actionUrl": null,
            "recordings": [],
            "key": "Hearing",
            "isMajor": true,
            "hearing": true
        },
        {
            "id": "SB3-0024",
            "bill": "SB 3",
            "date": "01/23/2023",
            "description": "Hearing",
            "posession": "senate",
            "committee": "Senate Finance and Claims",
            "actionUrl": null,
            "recordings": [],
            "key": "Hearing",
            "isMajor": true,
            "hearing": true
        },
        {
            "id": "SB6-0030",
            "bill": "SB 6",
            "date": "01/24/2023",
            "description": "Hearing",
            "posession": "house",
            "committee": "House Human Services",
            "actionUrl": null,
            "recordings": [],
            "key": "Hearing",
            "isMajor": true,
            "hearing": true
        },
        {
            "id": "SB18-0023",
            "bill": "SB 18",
            "date": "01/25/2023",
            "description": "Hearing",
            "posession": "house",
            "committee": "House State Administration",
            "actionUrl": null,
            "recordings": [],
            "key": "Hearing",
            "isMajor": true,
            "hearing": true
        },
        {
            "id": "SB20-0033",
            "bill": "SB 20",
            "date": "01/26/2023",
            "description": "Hearing",
            "posession": "house",
            "committee": "House Business and Labor",
            "actionUrl": null,
            "recordings": [],
            "key": "Hearing",
            "isMajor": true,
            "hearing": true
        },
        {
            "id": "SB21-0029",
            "bill": "SB 21",
            "date": "01/23/2023",
            "description": "Hearing",
            "posession": "senate",
            "committee": "Senate Finance and Claims",
            "actionUrl": null,
            "recordings": [],
            "key": "Hearing",
            "isMajor": true,
            "hearing": true
        },
        {
            "id": "SB34-0025",
            "bill": "SB 34",
            "date": "01/23/2023",
            "description": "Hearing",
            "posession": "house",
            "committee": "House Human Services",
            "actionUrl": null,
            "recordings": [],
            "key": "Hearing",
            "isMajor": true,
            "hearing": true
        },
        {
            "id": "SB35-0024",
            "bill": "SB 35",
            "date": "01/25/2023",
            "description": "Hearing",
            "posession": "house",
            "committee": "House Business and Labor",
            "actionUrl": null,
            "recordings": [],
            "key": "Hearing",
            "isMajor": true,
            "hearing": true
        },
        {
            "id": "SB40-0023",
            "bill": "SB 40",
            "date": "01/25/2023",
            "description": "Hearing",
            "posession": "house",
            "committee": "House State Administration",
            "actionUrl": null,
            "recordings": [],
            "key": "Hearing",
            "isMajor": true,
            "hearing": true
        },
        {
            "id": "SB45-0024",
            "bill": "SB 45",
            "date": "01/24/2023",
            "description": "Hearing",
            "posession": "house",
            "committee": "House Human Services",
            "actionUrl": null,
            "recordings": [],
            "key": "Hearing",
            "isMajor": true,
            "hearing": true
        },
        {
            "id": "SB51-0014",
            "bill": "SB 51",
            "date": "01/25/2023",
            "description": "Hearing",
            "posession": "senate",
            "committee": "Senate State Administration",
            "actionUrl": null,
            "recordings": [],
            "key": "Hearing",
            "isMajor": true,
            "hearing": true
        },
        {
            "id": "SB55-0019",
            "bill": "SB 55",
            "date": "01/25/2023",
            "description": "Hearing",
            "posession": "senate",
            "committee": "Senate Natural Resources",
            "actionUrl": null,
            "recordings": [],
            "key": "Hearing",
            "isMajor": true,
            "hearing": true
        },
        {
            "id": "SB58-0024",
            "bill": "SB 58",
            "date": "01/23/2023",
            "description": "Hearing",
            "posession": "senate",
            "committee": "Senate Finance and Claims",
            "actionUrl": null,
            "recordings": [],
            "key": "Hearing",
            "isMajor": true,
            "hearing": true
        },
        {
            "id": "SB62-0026",
            "bill": "SB 62",
            "date": "01/24/2023",
            "description": "Hearing",
            "posession": "house",
            "committee": "House Taxation",
            "actionUrl": null,
            "recordings": [],
            "key": "Hearing",
            "isMajor": true,
            "hearing": true
        },
        {
            "id": "SB70-0024",
            "bill": "SB 70",
            "date": "01/23/2023",
            "description": "Hearing",
            "posession": "senate",
            "committee": "Senate Finance and Claims",
            "actionUrl": null,
            "recordings": [],
            "key": "Hearing",
            "isMajor": true,
            "hearing": true
        },
        {
            "id": "SB80-0029",
            "bill": "SB 80",
            "date": "01/25/2023",
            "description": "Hearing",
            "posession": "house",
            "committee": "House Business and Labor",
            "actionUrl": null,
            "recordings": [],
            "key": "Hearing",
            "isMajor": true,
            "hearing": true
        },
        {
            "id": "SB83-0013",
            "bill": "SB 83",
            "date": "01/23/2023",
            "description": "Hearing",
            "posession": "senate",
            "committee": "Senate Natural Resources",
            "actionUrl": null,
            "recordings": [],
            "key": "Hearing",
            "isMajor": true,
            "hearing": true
        },
        {
            "id": "SB90-0022",
            "bill": "SB 90",
            "date": "01/24/2023",
            "description": "Hearing",
            "posession": "senate",
            "committee": "Senate Business, Labor, and Economic Affairs",
            "actionUrl": null,
            "recordings": [],
            "key": "Hearing",
            "isMajor": true,
            "hearing": true
        },
        {
            "id": "SB95-0026",
            "bill": "SB 95",
            "date": "01/23/2023",
            "description": "Hearing",
            "posession": "senate",
            "committee": "Senate Finance and Claims",
            "actionUrl": null,
            "recordings": [],
            "key": "Hearing",
            "isMajor": true,
            "hearing": true
        },
        {
            "id": "SB102-0030",
            "bill": "SB 102",
            "date": "01/25/2023",
            "description": "Hearing",
            "posession": "house",
            "committee": "House Business and Labor",
            "actionUrl": null,
            "recordings": [],
            "key": "Hearing",
            "isMajor": true,
            "hearing": true
        },
        {
            "id": "SB129-0016",
            "bill": "SB 129",
            "date": "01/20/2023",
            "description": "Hearing",
            "posession": "senate",
            "committee": "Senate Education and Cultural Resources",
            "actionUrl": null,
            "recordings": [],
            "key": "Hearing",
            "isMajor": true,
            "hearing": true
        },
        {
            "id": "SB140-0017",
            "bill": "SB 140",
            "date": "01/20/2023",
            "description": "Hearing",
            "posession": "senate",
            "committee": "Senate Business, Labor, and Economic Affairs",
            "actionUrl": null,
            "recordings": [],
            "key": "Hearing",
            "isMajor": true,
            "hearing": true
        },
        {
            "id": "SB153-0022",
            "bill": "SB 153",
            "date": "01/23/2023",
            "description": "Hearing",
            "posession": "senate",
            "committee": "Senate State Administration",
            "actionUrl": null,
            "recordings": [],
            "key": "Hearing",
            "isMajor": true,
            "hearing": true
        },
        {
            "id": "SB156-0017",
            "bill": "SB 156",
            "date": "01/23/2023",
            "description": "Hearing",
            "posession": "senate",
            "committee": "Senate State Administration",
            "actionUrl": null,
            "recordings": [],
            "key": "Hearing",
            "isMajor": true,
            "hearing": true
        },
        {
            "id": "SB161-0025",
            "bill": "SB 161",
            "date": "01/25/2023",
            "description": "Hearing",
            "posession": "senate",
            "committee": "Senate Business, Labor, and Economic Affairs",
            "actionUrl": null,
            "recordings": [],
            "key": "Hearing",
            "isMajor": true,
            "hearing": true
        },
        {
            "id": "SB162-0023",
            "bill": "SB 162",
            "date": "01/20/2023",
            "description": "Hearing",
            "posession": "senate",
            "committee": "Senate Public Health, Welfare and Safety",
            "actionUrl": null,
            "recordings": [],
            "key": "Hearing",
            "isMajor": true,
            "hearing": true
        },
        {
            "id": "SB163-0023",
            "bill": "SB 163",
            "date": "01/23/2023",
            "description": "Hearing",
            "posession": "senate",
            "committee": "Senate Public Health, Welfare and Safety",
            "actionUrl": null,
            "recordings": [],
            "key": "Hearing",
            "isMajor": true,
            "hearing": true
        },
        {
            "id": "SB165-0018",
            "bill": "SB 165",
            "date": "01/25/2023",
            "description": "Hearing",
            "posession": "senate",
            "committee": "Senate Business, Labor, and Economic Affairs",
            "actionUrl": null,
            "recordings": [],
            "key": "Hearing",
            "isMajor": true,
            "hearing": true
        },
        {
            "id": "SB167-0017",
            "bill": "SB 167",
            "date": "01/20/2023",
            "description": "Hearing",
            "posession": "senate",
            "committee": "Senate Business, Labor, and Economic Affairs",
            "actionUrl": null,
            "recordings": [],
            "key": "Hearing",
            "isMajor": true,
            "hearing": true
        },
        {
            "id": "SB174-0021",
            "bill": "SB 174",
            "date": "01/20/2023",
            "description": "Hearing",
            "posession": "senate",
            "committee": "Senate Business, Labor, and Economic Affairs",
            "actionUrl": null,
            "recordings": [],
            "key": "Hearing",
            "isMajor": true,
            "hearing": true
        },
        {
            "id": "SB177-0020",
            "bill": "SB 177",
            "date": "01/25/2023",
            "description": "Hearing",
            "posession": "senate",
            "committee": "Senate Business, Labor, and Economic Affairs",
            "actionUrl": null,
            "recordings": [],
            "key": "Hearing",
            "isMajor": true,
            "hearing": true
        },
        {
            "id": "SB178-0018",
            "bill": "SB 178",
            "date": "01/25/2023",
            "description": "Hearing",
            "posession": "senate",
            "committee": "Senate Business, Labor, and Economic Affairs",
            "actionUrl": null,
            "recordings": [],
            "key": "Hearing",
            "isMajor": true,
            "hearing": true
        },
        {
            "id": "SB179-0017",
            "bill": "SB 179",
            "date": "01/24/2023",
            "description": "Hearing",
            "posession": "senate",
            "committee": "Senate Business, Labor, and Economic Affairs",
            "actionUrl": null,
            "recordings": [],
            "key": "Hearing",
            "isMajor": true,
            "hearing": true
        },
        {
            "id": "SB180-0021",
            "bill": "SB 180",
            "date": "01/23/2023",
            "description": "Hearing",
            "posession": "senate",
            "committee": "Senate Public Health, Welfare and Safety",
            "actionUrl": null,
            "recordings": [],
            "key": "Hearing",
            "isMajor": true,
            "hearing": true
        },
        {
            "id": "SB181-0017",
            "bill": "SB 181",
            "date": "01/23/2023",
            "description": "Hearing",
            "posession": "senate",
            "committee": "Senate Public Health, Welfare and Safety",
            "actionUrl": null,
            "recordings": [],
            "key": "Hearing",
            "isMajor": true,
            "hearing": true
        },
        {
            "id": "SB182-0020",
            "bill": "SB 182",
            "date": "01/24/2023",
            "description": "Hearing",
            "posession": "senate",
            "committee": "Senate Judiciary",
            "actionUrl": null,
            "recordings": [],
            "key": "Hearing",
            "isMajor": true,
            "hearing": true
        },
        {
            "id": "SB183-0024",
            "bill": "SB 183",
            "date": "01/20/2023",
            "description": "Hearing",
            "posession": "senate",
            "committee": "Senate Judiciary",
            "actionUrl": null,
            "recordings": [],
            "key": "Hearing",
            "isMajor": true,
            "hearing": true
        },
        {
            "id": "SB184-0018",
            "bill": "SB 184",
            "date": "01/24/2023",
            "description": "Hearing",
            "posession": "senate",
            "committee": "Senate Judiciary",
            "actionUrl": null,
            "recordings": [],
            "key": "Hearing",
            "isMajor": true,
            "hearing": true
        },
        {
            "id": "SB186-0020",
            "bill": "SB 186",
            "date": "01/23/2023",
            "description": "Hearing",
            "posession": "senate",
            "committee": "Senate Public Health, Welfare and Safety",
            "actionUrl": null,
            "recordings": [],
            "key": "Hearing",
            "isMajor": true,
            "hearing": true
        },
        {
            "id": "SB187-0022",
            "bill": "SB 187",
            "date": "01/20/2023",
            "description": "Hearing",
            "posession": "senate",
            "committee": "Senate Judiciary",
            "actionUrl": null,
            "recordings": [],
            "key": "Hearing",
            "isMajor": true,
            "hearing": true
        },
        {
            "id": "SB188-0018",
            "bill": "SB 188",
            "date": "01/25/2023",
            "description": "Hearing",
            "posession": "senate",
            "committee": "Senate Public Health, Welfare and Safety",
            "actionUrl": null,
            "recordings": [],
            "key": "Hearing",
            "isMajor": true,
            "hearing": true
        },
        {
            "id": "SB191-0030",
            "bill": "SB 191",
            "date": "01/24/2023",
            "description": "Hearing",
            "posession": "senate",
            "committee": "Senate Judiciary",
            "actionUrl": null,
            "recordings": [],
            "key": "Hearing",
            "isMajor": true,
            "hearing": true
        },
        {
            "id": "SB195-0018",
            "bill": "SB 195",
            "date": "01/23/2023",
            "description": "Hearing",
            "posession": "senate",
            "committee": "Senate Local Government",
            "actionUrl": null,
            "recordings": [],
            "key": "Hearing",
            "isMajor": true,
            "hearing": true
        },
        {
            "id": "SB196-0019",
            "bill": "SB 196",
            "date": "01/25/2023",
            "description": "Hearing",
            "posession": "senate",
            "committee": "Senate Public Health, Welfare and Safety",
            "actionUrl": null,
            "recordings": [],
            "key": "Hearing",
            "isMajor": true,
            "hearing": true
        },
        {
            "id": "SJ4-0027",
            "bill": "SJ 4",
            "date": "01/25/2023",
            "description": "Hearing",
            "posession": "house",
            "committee": "House State Administration",
            "actionUrl": null,
            "recordings": [],
            "key": "Hearing",
            "isMajor": true,
            "hearing": true
        },
        {
            "id": "SJ6-0019",
            "bill": "SJ 6",
            "date": "01/25/2023",
            "description": "Hearing",
            "posession": "senate",
            "committee": "Senate Education and Cultural Resources",
            "actionUrl": null,
            "recordings": [],
            "key": "Hearing",
            "isMajor": true,
            "hearing": true
        },
        {
            "id": "SJ7-0017",
            "bill": "SJ 7",
            "date": "01/23/2023",
            "description": "Hearing",
            "posession": "senate",
            "committee": "Senate State Administration",
            "actionUrl": null,
            "recordings": [],
            "key": "Hearing",
            "isMajor": true,
            "hearing": true
        },
        {
            "id": "SJ8-0019",
            "bill": "SJ 8",
            "date": "01/23/2023",
            "description": "Hearing",
            "posession": "senate",
            "committee": "Senate State Administration",
            "actionUrl": null,
            "recordings": [],
            "key": "Hearing",
            "isMajor": true,
            "hearing": true
        },
        {
            "id": "SR6-0015",
            "bill": "SR 6",
            "date": "01/25/2023",
            "description": "Hearing",
            "posession": "senate",
            "committee": "Senate Judiciary",
            "actionUrl": null,
            "recordings": [],
            "key": "Hearing",
            "isMajor": true,
            "hearing": true
        },
        {
            "id": "SR8-0015",
            "bill": "SR 8",
            "date": "01/25/2023",
            "description": "Hearing",
            "posession": "senate",
            "committee": "Senate Judiciary",
            "actionUrl": null,
            "recordings": [],
            "key": "Hearing",
            "isMajor": true,
            "hearing": true
        },
        {
            "id": "SR9-0015",
            "bill": "SR 9",
            "date": "01/25/2023",
            "description": "Hearing",
            "posession": "senate",
            "committee": "Senate Judiciary",
            "actionUrl": null,
            "recordings": [],
            "key": "Hearing",
            "isMajor": true,
            "hearing": true
        },
        {
            "id": "SR10-0015",
            "bill": "SR 10",
            "date": "01/25/2023",
            "description": "Hearing",
            "posession": "senate",
            "committee": "Senate Judiciary",
            "actionUrl": null,
            "recordings": [],
            "key": "Hearing",
            "isMajor": true,
            "hearing": true
        }
    ],
    "scheduledFloorDebates": [
        {
            "id": "HB74-0021",
            "bill": "HB 74",
            "date": "01/20/2023",
            "description": "Scheduled for 2nd Reading",
            "posession": "house",
            "committee": null,
            "actionUrl": null,
            "recordings": [],
            "key": "Scheduled for 2nd Reading",
            "scheduledForFloorDebate": true
        },
        {
            "id": "HB75-0021",
            "bill": "HB 75",
            "date": "01/20/2023",
            "description": "Scheduled for 2nd Reading",
            "posession": "house",
            "committee": null,
            "actionUrl": null,
            "recordings": [],
            "key": "Scheduled for 2nd Reading",
            "scheduledForFloorDebate": true
        },
        {
            "id": "HB82-0023",
            "bill": "HB 82",
            "date": "01/20/2023",
            "description": "Scheduled for 2nd Reading",
            "posession": "house",
            "committee": null,
            "actionUrl": null,
            "recordings": [],
            "key": "Scheduled for 2nd Reading",
            "scheduledForFloorDebate": true
        },
        {
            "id": "HB151-0018",
            "bill": "HB 151",
            "date": "01/20/2023",
            "description": "Scheduled for 2nd Reading",
            "posession": "house",
            "committee": null,
            "actionUrl": null,
            "recordings": [],
            "key": "Scheduled for 2nd Reading",
            "scheduledForFloorDebate": true
        },
        {
            "id": "HB169-0021",
            "bill": "HB 169",
            "date": "01/20/2023",
            "description": "Scheduled for 2nd Reading",
            "posession": "house",
            "committee": null,
            "actionUrl": null,
            "recordings": [],
            "key": "Scheduled for 2nd Reading",
            "scheduledForFloorDebate": true
        },
        {
            "id": "HB170-0024",
            "bill": "HB 170",
            "date": "01/20/2023",
            "description": "Scheduled for 2nd Reading",
            "posession": "house",
            "committee": null,
            "actionUrl": null,
            "recordings": [],
            "key": "Scheduled for 2nd Reading",
            "scheduledForFloorDebate": true
        },
        {
            "id": "HB178-0021",
            "bill": "HB 178",
            "date": "01/20/2023",
            "description": "Scheduled for 2nd Reading",
            "posession": "house",
            "committee": null,
            "actionUrl": null,
            "recordings": [],
            "key": "Scheduled for 2nd Reading",
            "scheduledForFloorDebate": true
        },
        {
            "id": "HB183-0025",
            "bill": "HB 183",
            "date": "01/20/2023",
            "description": "Scheduled for 2nd Reading",
            "posession": "house",
            "committee": null,
            "actionUrl": null,
            "recordings": [],
            "key": "Scheduled for 2nd Reading",
            "scheduledForFloorDebate": true
        },
        {
            "id": "HB188-0029",
            "bill": "HB 188",
            "date": "01/20/2023",
            "description": "Scheduled for 2nd Reading",
            "posession": "house",
            "committee": null,
            "actionUrl": null,
            "recordings": [],
            "key": "Scheduled for 2nd Reading",
            "scheduledForFloorDebate": true
        },
        {
            "id": "HB205-0023",
            "bill": "HB 205",
            "date": "01/20/2023",
            "description": "Scheduled for 2nd Reading",
            "posession": "house",
            "committee": null,
            "actionUrl": null,
            "recordings": [],
            "key": "Scheduled for 2nd Reading",
            "scheduledForFloorDebate": true
        },
        {
            "id": "HB209-0026",
            "bill": "HB 209",
            "date": "01/20/2023",
            "description": "Scheduled for 2nd Reading",
            "posession": "house",
            "committee": null,
            "actionUrl": null,
            "recordings": [],
            "key": "Scheduled for 2nd Reading",
            "scheduledForFloorDebate": true
        },
        {
            "id": "SB17-0017",
            "bill": "SB 17",
            "date": "01/20/2023",
            "description": "Scheduled for 2nd Reading",
            "posession": "senate",
            "committee": null,
            "actionUrl": null,
            "recordings": [],
            "key": "Scheduled for 2nd Reading",
            "scheduledForFloorDebate": true
        },
        {
            "id": "SB33-0022",
            "bill": "SB 33",
            "date": "01/20/2023",
            "description": "Scheduled for 2nd Reading",
            "posession": "senate",
            "committee": null,
            "actionUrl": null,
            "recordings": [],
            "key": "Scheduled for 2nd Reading",
            "scheduledForFloorDebate": true
        },
        {
            "id": "SB50-0020",
            "bill": "SB 50",
            "date": "01/20/2023",
            "description": "Scheduled for 2nd Reading",
            "posession": "senate",
            "committee": null,
            "actionUrl": null,
            "recordings": [],
            "key": "Scheduled for 2nd Reading",
            "scheduledForFloorDebate": true
        },
        {
            "id": "SB64-0018",
            "bill": "SB 64",
            "date": "01/20/2023",
            "description": "Scheduled for 2nd Reading",
            "posession": "senate",
            "committee": null,
            "actionUrl": null,
            "recordings": [],
            "key": "Scheduled for 2nd Reading",
            "scheduledForFloorDebate": true
        },
        {
            "id": "SB81-0018",
            "bill": "SB 81",
            "date": "01/20/2023",
            "description": "Scheduled for 2nd Reading",
            "posession": "senate",
            "committee": null,
            "actionUrl": null,
            "recordings": [],
            "key": "Scheduled for 2nd Reading",
            "scheduledForFloorDebate": true
        },
        {
            "id": "SB132-0026",
            "bill": "SB 132",
            "date": "01/20/2023",
            "description": "Scheduled for 2nd Reading",
            "posession": "senate",
            "committee": null,
            "actionUrl": null,
            "recordings": [],
            "key": "Scheduled for 2nd Reading",
            "scheduledForFloorDebate": true
        },
        {
            "id": "SB149-0020",
            "bill": "SB 149",
            "date": "01/20/2023",
            "description": "Scheduled for 2nd Reading",
            "posession": "senate",
            "committee": null,
            "actionUrl": null,
            "recordings": [],
            "key": "Scheduled for 2nd Reading",
            "scheduledForFloorDebate": true
        },
        {
            "id": "SB155-0025",
            "bill": "SB 155",
            "date": "01/20/2023",
            "description": "Scheduled for 2nd Reading",
            "posession": "senate",
            "committee": null,
            "actionUrl": null,
            "recordings": [],
            "key": "Scheduled for 2nd Reading",
            "scheduledForFloorDebate": true
        },
        {
            "id": "SB155-0026",
            "bill": "SB 155",
            "date": "01/20/2023",
            "description": "Scheduled for 2nd Reading",
            "posession": "senate",
            "committee": null,
            "actionUrl": null,
            "recordings": [],
            "key": "Scheduled for 2nd Reading",
            "scheduledForFloorDebate": true
        },
        {
            "id": "SJ1-0034",
            "bill": "SJ 1",
            "date": "01/20/2023",
            "description": "Scheduled for 2nd Reading",
            "posession": "house",
            "committee": null,
            "actionUrl": null,
            "recordings": [],
            "key": "Scheduled for 2nd Reading",
            "scheduledForFloorDebate": true
        }
    ],
    "scheduledFinalVotes": [
        {
            "id": "HB74-0023",
            "bill": "HB 74",
            "date": "01/23/2023",
            "description": "Scheduled for 3rd Reading",
            "posession": "house",
            "committee": null,
            "actionUrl": null,
            "recordings": [],
            "key": "Scheduled for 3rd Reading",
            "scheduledForFinalVote": true
        },
        {
            "id": "HB75-0023",
            "bill": "HB 75",
            "date": "01/23/2023",
            "description": "Scheduled for 3rd Reading",
            "posession": "house",
            "committee": null,
            "actionUrl": null,
            "recordings": [],
            "key": "Scheduled for 3rd Reading",
            "scheduledForFinalVote": true
        },
        {
            "id": "HB93-0021",
            "bill": "HB 93",
            "date": "01/20/2023",
            "description": "Scheduled for 3rd Reading",
            "posession": "house",
            "committee": null,
            "actionUrl": null,
            "recordings": [],
            "key": "Scheduled for 3rd Reading",
            "scheduledForFinalVote": true
        },
        {
            "id": "HB94-0026",
            "bill": "HB 94",
            "date": "01/20/2023",
            "description": "Scheduled for 3rd Reading",
            "posession": "house",
            "committee": null,
            "actionUrl": null,
            "recordings": [],
            "key": "Scheduled for 3rd Reading",
            "scheduledForFinalVote": true
        },
        {
            "id": "HB102-0019",
            "bill": "HB 102",
            "date": "01/20/2023",
            "description": "Scheduled for 3rd Reading",
            "posession": "house",
            "committee": null,
            "actionUrl": null,
            "recordings": [],
            "key": "Scheduled for 3rd Reading",
            "scheduledForFinalVote": true
        },
        {
            "id": "HB105-0024",
            "bill": "HB 105",
            "date": "01/20/2023",
            "description": "Scheduled for 3rd Reading",
            "posession": "house",
            "committee": null,
            "actionUrl": null,
            "recordings": [],
            "key": "Scheduled for 3rd Reading",
            "scheduledForFinalVote": true
        },
        {
            "id": "HB108-0025",
            "bill": "HB 108",
            "date": "01/20/2023",
            "description": "Scheduled for 3rd Reading",
            "posession": "house",
            "committee": null,
            "actionUrl": null,
            "recordings": [],
            "key": "Scheduled for 3rd Reading",
            "scheduledForFinalVote": true
        },
        {
            "id": "HB109-0022",
            "bill": "HB 109",
            "date": "01/20/2023",
            "description": "Scheduled for 3rd Reading",
            "posession": "house",
            "committee": null,
            "actionUrl": null,
            "recordings": [],
            "key": "Scheduled for 3rd Reading",
            "scheduledForFinalVote": true
        },
        {
            "id": "HB116-0019",
            "bill": "HB 116",
            "date": "01/20/2023",
            "description": "Scheduled for 3rd Reading",
            "posession": "house",
            "committee": null,
            "actionUrl": null,
            "recordings": [],
            "key": "Scheduled for 3rd Reading",
            "scheduledForFinalVote": true
        },
        {
            "id": "HB134-0018",
            "bill": "HB 134",
            "date": "01/20/2023",
            "description": "Scheduled for 3rd Reading",
            "posession": "house",
            "committee": null,
            "actionUrl": null,
            "recordings": [],
            "key": "Scheduled for 3rd Reading",
            "scheduledForFinalVote": true
        },
        {
            "id": "HB143-0023",
            "bill": "HB 143",
            "date": "01/20/2023",
            "description": "Scheduled for 3rd Reading",
            "posession": "house",
            "committee": null,
            "actionUrl": null,
            "recordings": [],
            "key": "Scheduled for 3rd Reading",
            "scheduledForFinalVote": true
        },
        {
            "id": "HB151-0021",
            "bill": "HB 151",
            "date": "01/23/2023",
            "description": "Scheduled for 3rd Reading",
            "posession": "house",
            "committee": null,
            "actionUrl": null,
            "recordings": [],
            "key": "Scheduled for 3rd Reading",
            "scheduledForFinalVote": true
        },
        {
            "id": "HB169-0023",
            "bill": "HB 169",
            "date": "01/23/2023",
            "description": "Scheduled for 3rd Reading",
            "posession": "house",
            "committee": null,
            "actionUrl": null,
            "recordings": [],
            "key": "Scheduled for 3rd Reading",
            "scheduledForFinalVote": true
        },
        {
            "id": "HB170-0026",
            "bill": "HB 170",
            "date": "01/23/2023",
            "description": "Scheduled for 3rd Reading",
            "posession": "house",
            "committee": null,
            "actionUrl": null,
            "recordings": [],
            "key": "Scheduled for 3rd Reading",
            "scheduledForFinalVote": true
        },
        {
            "id": "HB178-0023",
            "bill": "HB 178",
            "date": "01/23/2023",
            "description": "Scheduled for 3rd Reading",
            "posession": "house",
            "committee": null,
            "actionUrl": null,
            "recordings": [],
            "key": "Scheduled for 3rd Reading",
            "scheduledForFinalVote": true
        },
        {
            "id": "HB183-0027",
            "bill": "HB 183",
            "date": "01/23/2023",
            "description": "Scheduled for 3rd Reading",
            "posession": "house",
            "committee": null,
            "actionUrl": null,
            "recordings": [],
            "key": "Scheduled for 3rd Reading",
            "scheduledForFinalVote": true
        },
        {
            "id": "HB205-0025",
            "bill": "HB 205",
            "date": "01/23/2023",
            "description": "Scheduled for 3rd Reading",
            "posession": "house",
            "committee": null,
            "actionUrl": null,
            "recordings": [],
            "key": "Scheduled for 3rd Reading",
            "scheduledForFinalVote": true
        },
        {
            "id": "SB17-0019",
            "bill": "SB 17",
            "date": "01/23/2023",
            "description": "Scheduled for 3rd Reading",
            "posession": "senate",
            "committee": null,
            "actionUrl": null,
            "recordings": [],
            "key": "Scheduled for 3rd Reading",
            "scheduledForFinalVote": true
        },
        {
            "id": "SB27-0023",
            "bill": "SB 27",
            "date": "01/20/2023",
            "description": "Scheduled for 3rd Reading",
            "posession": "senate",
            "committee": null,
            "actionUrl": null,
            "recordings": [],
            "key": "Scheduled for 3rd Reading",
            "scheduledForFinalVote": true
        },
        {
            "id": "SB33-0024",
            "bill": "SB 33",
            "date": "01/23/2023",
            "description": "Scheduled for 3rd Reading",
            "posession": "senate",
            "committee": null,
            "actionUrl": null,
            "recordings": [],
            "key": "Scheduled for 3rd Reading",
            "scheduledForFinalVote": true
        },
        {
            "id": "SB50-0022",
            "bill": "SB 50",
            "date": "01/23/2023",
            "description": "Scheduled for 3rd Reading",
            "posession": "senate",
            "committee": null,
            "actionUrl": null,
            "recordings": [],
            "key": "Scheduled for 3rd Reading",
            "scheduledForFinalVote": true
        },
        {
            "id": "SB64-0020",
            "bill": "SB 64",
            "date": "01/23/2023",
            "description": "Scheduled for 3rd Reading",
            "posession": "senate",
            "committee": null,
            "actionUrl": null,
            "recordings": [],
            "key": "Scheduled for 3rd Reading",
            "scheduledForFinalVote": true
        },
        {
            "id": "SB78-0027",
            "bill": "SB 78",
            "date": "01/20/2023",
            "description": "Scheduled for 3rd Reading",
            "posession": "senate",
            "committee": null,
            "actionUrl": null,
            "recordings": [],
            "key": "Scheduled for 3rd Reading",
            "scheduledForFinalVote": true
        },
        {
            "id": "SB81-0020",
            "bill": "SB 81",
            "date": "01/23/2023",
            "description": "Scheduled for 3rd Reading",
            "posession": "senate",
            "committee": null,
            "actionUrl": null,
            "recordings": [],
            "key": "Scheduled for 3rd Reading",
            "scheduledForFinalVote": true
        },
        {
            "id": "SB111-0029",
            "bill": "SB 111",
            "date": "01/20/2023",
            "description": "Scheduled for 3rd Reading",
            "posession": "senate",
            "committee": null,
            "actionUrl": null,
            "recordings": [],
            "key": "Scheduled for 3rd Reading",
            "scheduledForFinalVote": true
        },
        {
            "id": "SB116-0024",
            "bill": "SB 116",
            "date": "01/20/2023",
            "description": "Scheduled for 3rd Reading",
            "posession": "senate",
            "committee": null,
            "actionUrl": null,
            "recordings": [],
            "key": "Scheduled for 3rd Reading",
            "scheduledForFinalVote": true
        },
        {
            "id": "SB130-0033",
            "bill": "SB 130",
            "date": "01/20/2023",
            "description": "Scheduled for 3rd Reading",
            "posession": "senate",
            "committee": null,
            "actionUrl": null,
            "recordings": [],
            "key": "Scheduled for 3rd Reading",
            "scheduledForFinalVote": true
        },
        {
            "id": "SB131-0022",
            "bill": "SB 131",
            "date": "01/20/2023",
            "description": "Scheduled for 3rd Reading",
            "posession": "senate",
            "committee": null,
            "actionUrl": null,
            "recordings": [],
            "key": "Scheduled for 3rd Reading",
            "scheduledForFinalVote": true
        },
        {
            "id": "SB149-0022",
            "bill": "SB 149",
            "date": "01/23/2023",
            "description": "Scheduled for 3rd Reading",
            "posession": "senate",
            "committee": null,
            "actionUrl": null,
            "recordings": [],
            "key": "Scheduled for 3rd Reading",
            "scheduledForFinalVote": true
        },
        {
            "id": "SB152-0025",
            "bill": "SB 152",
            "date": "01/20/2023",
            "description": "Scheduled for 3rd Reading",
            "posession": "senate",
            "committee": null,
            "actionUrl": null,
            "recordings": [],
            "key": "Scheduled for 3rd Reading",
            "scheduledForFinalVote": true
        },
        {
            "id": "SJ1-0038",
            "bill": "SJ 1",
            "date": "01/23/2023",
            "description": "Scheduled for 3rd Reading",
            "posession": "house",
            "committee": null,
            "actionUrl": null,
            "recordings": [],
            "key": "Scheduled for 3rd Reading",
            "scheduledForFinalVote": true
        },
        {
            "id": "SJ3-0023",
            "bill": "SJ 3",
            "date": "01/20/2023",
            "description": "Scheduled for 3rd Reading",
            "posession": "senate",
            "committee": null,
            "actionUrl": null,
            "recordings": [],
            "key": "Scheduled for 3rd Reading",
            "scheduledForFinalVote": true
        }
    ]
}